requests_connection_manager/__init__.py
requests_connection_manager/exceptions.py
requests_connection_manager/manager.py
requests_connection_manager/plugins.py
requests_connection_manager/utils.py
requests_connection_manager/version.py
requests_connection_manager-1.0.0.dist-info/METADATA
requests_connection_manager-1.0.0.dist-info/WHEEL
requests_connection_manager-1.0.0.dist-info/RECORD
