Metadata-Version: 2.3
Name: requests-connection-manager
Version: 1.0.0
Summary: A Python package that extends requests with connection pooling, retries, rate limiting, and circuit breaker functionality
License: MIT
Keywords: requests,http,connection,pooling,retry,rate-limiting,circuit-breaker
Author: Charles Gude
Author-email: charles@example.com
Requires-Python: >=3.9,<4.0
Classifier: Development Status :: 4 - Beta
Classifier: Intended Audience :: Developers
Classifier: License :: OSI Approved :: MIT License
Classifier: Programming Language :: Python :: 3
Classifier: Programming Language :: Python :: 3.9
Classifier: Programming Language :: Python :: 3.10
Classifier: Programming Language :: Python :: 3.11
Classifier: Programming Language :: Python :: 3.12
Classifier: Programming Language :: Python :: 3.13
Classifier: Programming Language :: Python :: 3.8
Classifier: Topic :: Internet :: WWW/HTTP
Classifier: Topic :: Software Development :: Libraries :: Python Modules
Requires-Dist: pybreaker (>=1.2.0,<2.0.0)
Requires-Dist: ratelimit (>=2.2.1,<3.0.0)
Requires-Dist: requests (>=2.25.0,<3.0.0)
Requires-Dist: urllib3 (>=1.26.0,<2.0.0)
Project-URL: Homepage, https://github.com/charlesgude/requests-api-manager
Project-URL: Repository, https://github.com/charlesgude/requests-api-manager
